feature_mining/__init__.py
feature_mining/em_base.py
feature_mining/em_original.py
feature_mining/em_vector.py
feature_mining/em_vector_by_feature.py
feature_mining/fm.py
feature_mining/gflm_tagger.py
feature_mining/parse_and_model.py
feature_mining/data/iPod.final
feature_mining-0.1.1.data/data/data/iPod.final
feature_mining-0.1.1.dist-info/LICENSE
feature_mining-0.1.1.dist-info/METADATA
feature_mining-0.1.1.dist-info/WHEEL
feature_mining-0.1.1.dist-info/dependency_links.txt
feature_mining-0.1.1.dist-info/top_level.txt
feature_mining-0.1.1.dist-info/RECORD
